bidscoin/__init__.py
bidscoin/bcoin.py
bidscoin/bids.py
bidscoin/bidscoin.ico
bidscoin/bidscoin_logo.png
bidscoin/bidscoiner.py
bidscoin/bidseditor.py
bidscoin/bidsmapper.py
bidscoin/due.py
bidscoin/rightarrow.png
bidscoin/bidsapps/__init__.py
bidscoin/bidsapps/deface.py
bidscoin/bidsapps/echocombine.py
bidscoin/bidsapps/fixmeta.py
bidscoin/bidsapps/medeface.py
bidscoin/bidsapps/skullstrip.py
bidscoin/bidsapps/slicereport.py
bidscoin/cli/__init__.py
bidscoin/cli/_bcoin.py
bidscoin/cli/_bidscoiner.py
bidscoin/cli/_bidseditor.py
bidscoin/cli/_bidsmapper.py
bidscoin/cli/_bidsparticipants.py
bidscoin/cli/_deface.py
bidscoin/cli/_dicomsort.py
bidscoin/cli/_echocombine.py
bidscoin/cli/_fixmeta.py
bidscoin/cli/_medeface.py
bidscoin/cli/_physio2tsv.py
bidscoin/cli/_plotphysio.py
bidscoin/cli/_rawmapper.py
bidscoin/cli/_skullstrip.py
bidscoin/cli/_slicereport.py
bidscoin/heuristics/__init__.py
bidscoin/heuristics/bidsmap_bids2bids.yaml
bidscoin/heuristics/bidsmap_dccn.yaml
bidscoin/heuristics/bidsmap_sst.yaml
bidscoin/heuristics/schema.json
bidscoin/plugins/__init__.py
bidscoin/plugins/dcm2niix2bids.py
bidscoin/plugins/events2bids.py
bidscoin/plugins/nibabel2bids.py
bidscoin/plugins/spec2nii2bids.py
bidscoin/schema/BIDS_VERSION
bidscoin/schema/SCHEMA_VERSION
bidscoin/schema/__init__.py
bidscoin/schema/meta/associations.yaml
bidscoin/schema/meta/context.yaml
bidscoin/schema/meta/expression_tests.yaml
bidscoin/schema/meta/versions.yaml
bidscoin/schema/objects/__init__.py
bidscoin/schema/objects/columns.yaml
bidscoin/schema/objects/common_principles.yaml
bidscoin/schema/objects/datatypes.yaml
bidscoin/schema/objects/entities.yaml
bidscoin/schema/objects/enums.yaml
bidscoin/schema/objects/extensions.yaml
bidscoin/schema/objects/files.yaml
bidscoin/schema/objects/formats.yaml
bidscoin/schema/objects/metadata.yaml
bidscoin/schema/objects/modalities.yaml
bidscoin/schema/objects/suffixes.yaml
bidscoin/schema/rules/__init__.py
bidscoin/schema/rules/common_principles.yaml
bidscoin-4.6.1.dist-info/licenses/LICENSE.txt
bidscoin-4.6.1.dist-info/METADATA
bidscoin-4.6.1.dist-info/WHEEL
bidscoin-4.6.1.dist-info/entry_points.txt
bidscoin-4.6.1.dist-info/top_level.txt
bidscoin-4.6.1.dist-info/RECORD
