Metadata-Version: 2.4
Name: bidscoin
Version: 4.6.1
Summary: Converts and organises raw MRI data-sets according to the Brain Imaging Data Structure (BIDS)
Author: Marcel Zwiers
Author-email: m.zwiers@donders.ru.nl
License:                     GNU GENERAL PUBLIC LICENSE
Project-URL: documentation, https://bidscoin.readthedocs.io
Project-URL: homepage, https://github.com/Donders-Institute/bidscoin
Project-URL: repository, https://github.com/Donders-Institute/bidscoin
Keywords: bids,mri,imaging,neuroimaging,dicom,par,rec,PsychoPy,NeuroBS,nifti,bidsapp,defacing,echo-combination,skull-stripping,HPC
Classifier: Programming Language :: Python :: 3
Classifier: License :: OSI Approved :: GNU General Public License v3 or later (GPLv3+)
Classifier: Operating System :: OS Independent
Classifier: Intended Audience :: Science/Research
Requires-Python: >=3.9
License-File: LICENSE.txt
Requires-Dist: pandas
Requires-Dist: matplotlib
Requires-Dist: numpy
Requires-Dist: pydicom>=2
Requires-Dist: PyQt6
Requires-Dist: pyyaml
Requires-Dist: tomli>=1.1.0; python_version < "3.11"
Requires-Dist: coloredlogs
Requires-Dist: tqdm>=4.60.0
Requires-Dist: multiecho>=0.25
Requires-Dist: python-dateutil
Requires-Dist: nibabel
Requires-Dist: bids-validator
Requires-Dist: jsonschema
Requires-Dist: bidsschematools
Requires-Dist: drmaa
Requires-Dist: duecredit
Provides-Extra: dcm2niix2bids
Requires-Dist: dcm2niix; extra == "dcm2niix2bids"
Provides-Extra: spec2nii2bids
Requires-Dist: spec2nii>=0.6.1; extra == "spec2nii2bids"
Provides-Extra: deface
Requires-Dist: pydeface; extra == "deface"
Provides-Extra: all
Requires-Dist: bidscoin[dcm2niix2bids,deface,spec2nii2bids]; extra == "all"
Provides-Extra: dev
Requires-Dist: bidscoin[deface,spec2nii2bids]; extra == "dev"
Requires-Dist: tox; extra == "dev"
Requires-Dist: pytest; extra == "dev"
Requires-Dist: sphinx-rtd-theme; extra == "dev"
Requires-Dist: myst-parser; extra == "dev"
Requires-Dist: sphinx_design; extra == "dev"
Provides-Extra: extras
Requires-Dist: psychopy; extra == "extras"
Requires-Dist: dicom-parser; extra == "extras"
Dynamic: license-file
